README.rst
setup.py
ipinfo/__init__.py
ipinfo/utils.py
pyipinfo.egg-info/PKG-INFO
pyipinfo.egg-info/SOURCES.txt
pyipinfo.egg-info/dependency_links.txt
pyipinfo.egg-info/entry_points.txt
pyipinfo.egg-info/requires.txt
pyipinfo.egg-info/top_level.txt