Metadata-Version: 1.1
Name: pyipinfo
Version: 0.0.5
Summary: ipinfo.io in the command line
Home-page: https://github.com/juanpabloaj/pyipinfo
Author: JuanPablo AJ
Author-email: jpabloaj@gmail.com
License: MIT
Platform: UNKNOWN
Classifier: Programming Language :: Python :: 2.7
